setup.py
imathics/__init__.py
imathics/__main__.py
imathics/kernel.py
imathics/terminalapp.py
imathics.egg-info/PKG-INFO
imathics.egg-info/SOURCES.txt
imathics.egg-info/dependency_links.txt
imathics.egg-info/entry_points.txt
imathics.egg-info/requires.txt
imathics.egg-info/top_level.txt