Metadata-Version: 1.1
Name: imathics
Version: 0.1
Summary: A jupyter kernel for mathics
Home-page: http://www.mathics.github.io/
Author: Angus Griffith
Author-email: imathics@angusgriffith.com
License: UNKNOWN
Keywords: Mathematica,Wolfram,Interpreter,Shell,Math,CAS
Platform: UNKNOWN
Classifier: Intended Audience :: Developers
Classifier: Intended Audience :: Science/Research
Classifier: License :: OSI Approved :: GNU General Public License v3 (GPLv3)
Classifier: Programming Language :: Python
Classifier: Programming Language :: Python :: 2.7
Classifier: Programming Language :: Python :: 2 :: Only
Classifier: Topic :: Scientific/Engineering
Classifier: Topic :: Scientific/Engineering :: Mathematics
Classifier: Topic :: Scientific/Engineering :: Physics
